{"httpProtocol":"HTTP/1.1","clientAcceptEncoding":"gzip, deflate, br","requestPriority":"","edgeRequestKeepAliveStatus":1,"requestHeaderNames":{},"clientTcpRtt":1,"clientQuicRtt":0,"colo":"SIN","asn":8075,"asOrganization":"Microsoft Corporation","country":"SG","isEUCountry":false,"city":"Singapore","continent":"AS","timezone":"Asia/Singapore","longitude":"103.85007","latitude":"1.28967","postalCode":"018989","tlsVersion":"TLSv1.3","tlsCipher":"AEAD-AES256-GCM-SHA384","tlsClientRandom":"+2MaYOBA7vvCDnwW7OWpkSGdLxhrvJ10CXlVeoTIyJ8=","tlsClientCiphersSha1":"kXrN3VEKDdzz2cPKTQaKzpxVTxQ=","tlsClientExtensionsSha1":"1eY97BUYYO8vDaTfHQywB1pcNdM=","tlsClientExtensionsSha1Le":"u4wtEMFQBY18l3BzHAvORm+KGRw=","tlsExportedAuthenticator":{"clientHandshake":"ca1fb93e4348725233902840e83edec75afb47a18d3c4f75c0bf74987a45cc884c82b281ffe09fbea1c476132cbfbd94","serverHandshake":"24019aaa38b38fe5ffd5135b3eb468d8adf51d60f3f822575dc7694b9578f4720113ea7f70dd494617bd701082f6f364","clientFinished":"86b04c06308e8d11e58eddac513d8f25cccb348481c80c68d49628857252b67ea3c0b05b330ffb6cf4eead0ade73da77","serverFinished":"98df0df63efd526e4dfbe0f7187ca03408ea7c75b2eccf4196b7b6286757fbb90aabd3db32db34fa7a308be6bfebf3bc"},"tlsClientHelloLength":"1605","tlsClientAuth":{"certPresented":"0","certVerified":"NONE","certRevoked":"0","certIssuerDN":"","certSubjectDN":"","certIssuerDNRFC2253":"","certSubjectDNRFC2253":"","certIssuerDNLegacy":"","certSubjectDNLegacy":"","certSerial":"","certIssuerSerial":"","certSKI":"","certIssuerSKI":"","certFingerprintSHA1":"","certFingerprintSHA256":"","certNotBefore":"","certNotAfter":"","certRFC9440":"","certRFC9440TooLarge":false,"certChainRFC9440":"","certChainRFC9440TooLarge":false},"verifiedBotCategory":"","edgeL4":{"deliveryRate":2590084},"botManagement":{"corporateProxy":false,"verifiedBot":false,"jsDetection":{"passed":false},"staticResource":false,"detectionIds":{},"score":99}}